package_circle_to_polygon/__init__.py
package_circle_to_polygon-0.0.2.dist-info/LICENSE
package_circle_to_polygon-0.0.2.dist-info/METADATA
package_circle_to_polygon-0.0.2.dist-info/WHEEL
package_circle_to_polygon-0.0.2.dist-info/top_level.txt
package_circle_to_polygon-0.0.2.dist-info/RECORD
